Workbook

Sheet Principal
D4: CLIENTE | I4: FECHA | J4: 44134
D5: ASUNTO Nº | F5: CONCEPTO | I5: Rev: 0
D6: PV | F6: COSTE | G6: =+D32 -> 0 | H6: M. BRUTO | I6: =+D34 -> 0 | J6: =I6/E6 -> #DIV/0!
D7: Regulariz. | F7: K | G7: =E6/G6 -> #DIV/0!
D8: PV1 | E8: =E6+E7 -> 0 | F8: COSTE | G8: =+E32 -> 0 | H8: M.BRUTO | I8: =E8-G8 -> 0 | J8: =I8/E8 -> #DIV/0!
F9: K | G9: =E8/G8 -> #DIV/0!
D10: 1 | E10: 2 | F10: 3 | G10: 4 | H10: 5 | J10: 6=3-1 o 3-2
B11: BLOQUE | C11: CONCEPTO | D11: C. PREV | E11: REV. PREV | F11: PEDIDO | G11: FACTURADO | H11: PENDIENTE | J11: DESVIACION
B13: 901 | C13: GASTOS SUPERVISOR
B14: 921 | C14: EXPORTACION TEMPORAL HERRAMIENTAS
B15: 951 | C15: GASTOS VIAJE
B16: 961 | C16: GASTOS FINANCIEROS
B17: 962 | C17: GASTOS INGENIERIA
B18: 971 | C18: AVALES
C19: COMISIONES
B20: 981 | C20: TRANSPORTES | J20: =F20-D20 -> 0
C21: TOTAL | D21: =SUM(D13:D20) -> 0 | E21: =SUM(E13:E20) -> 0 | F21: =SUM(F13:F20) -> 0 | G21: =SUM(G13:G20) -> 0 | H21: =SUM(H13:H20) -> 0 | J21: =SUM(J13:J20) -> 0
B22: 0 | C22: FABRICACIONES TANQUES | J22: =F22-D22 -> 0
B23: 1 | C23: FABRICACIONES TECHOS | J23: =F23-D23 -> 0
B24: 2 | C24: FABRICACIONES [OTROS] | J24: =F24-D24 -> 0
B25: 3 | C25: MONTAJE | J25: =F25-D25 -> 0
B26: 4 | J26: =F26-D26 -> 0
B27: 5
B28: 6
B29: 7 | C29: TRANSPORTES | J29: =F29-D29 -> 0
C30: TOTAL | D30: =SUM(D22:D29) -> 0 | E30: =SUM(E22:E29) -> 0 | F30: =SUM(F22:F29) -> 0 | G30: =SUM(G22:G29) -> 0 | H30: =SUM(H22:H29) -> 0 | J30: =SUM(J22:J29) -> 0
C32: TOTAL | D32: =SUM(D21+D30) -> 0 | E32: =SUM(E21+E30) -> 0 | F32: =SUM(F21+F30) -> 0 | G32: =SUM(G21+G30) -> 0 | H32: =SUM(H21+H30) -> 0 | J32: =SUM(J21+J30) -> 0
C33: P. VENTA | D33: =E6 -> 0 | E33: =E6 -> 0 | F33: =E6 -> 0 | G33: =E8 -> 0
C34: M. BRUTO | D34: =D33-D32 -> 0 | E34: =E33-E32 -> 0 | F34: =F33-F32 -> 0 | G34: =G33-G32 -> 0
C35: CMV | D35: =D30+D20 -> 0 | E35: =E30+E20 -> 0 | F35: =F30+F20 -> 0 | G35: =G30+G20 -> 0
C36: M. NETO | D36: =D33-D35 -> 0 | E36: =E33-E35 -> 0 | F36: =F33-F35 -> 0 | G36: =G33-G35 -> 0 | I36: =(F30-G8)/G8 -> #DIV/0!
C37: K1 | D37: =D33/D32 -> #DIV/0! | E37: =E33/E32 -> #DIV/0! | F37: =F33/F32 -> #DIV/0! | G37: =G33/G32 -> #DIV/0!
C38: K2 | D38: =D33/D35 -> #DIV/0! | E38: =E33/E35 -> #DIV/0! | F38: =F33/F35 -> #DIV/0! | G38: =G33/G35 -> #DIV/0!

Sheet Forma de Pago
B2: PAGOS DEL CLIENTE
B3: Hito | C3: Concepto | D3: Momento de facturacion | E3: Forma de pago | F3: Porcentaje | G3: Importe sin Iva
B4: 1 | C4: Anticipo | F4: 0 | G4: =Principal!$E$8*F4 -> 0
B5: 2 | C5: Entrega | F5: 0 | G5: =Principal!$E$8*F5 -> 0
B6: 3 | C6: Finalización | F6: 0 | G6: =Principal!$E$8*F6 -> 0
B7: 4 | F7: 0 | G7: =Principal!$E$8*F7 -> 0
B8: 5 | F8: 0 | G8: =Principal!$E$8*F8 -> 0
B9: 6 | F9: 0 | G9: =Principal!$E$8*F9 -> 0
B10: 7 | F10: 0 | G10: =Principal!$E$8*F10 -> 0
B11: 8 | F11: 0 | G11: =Principal!$E$8*F11 -> 0
B12: 9 | F12: 0 | G12: =Principal!$E$8*F12 -> 0
B13: 10 | F13: 0 | G13: =Principal!$E$8*F13 -> 0
E14: Total | F14: =SUM(F4:F13) -> 0 | G14: =SUM(G4:G13) -> 0
B17: PAGOS
B18: Hito | C18: Concepto | D18: Momento de facturacion | E18: Forma de pago | F18: Porcentaje | G18: Importe sin Iva
B19: 1 | C19: =Principal!C22 -> FABRICACIONES TANQUES | F19: 1 | G19: =Principal!E22*F19 -> 0
B20: 2 | C20: =Principal!C23 -> FABRICACIONES TECHOS | F20: 1 | G20: =Principal!E23*F20 -> 0
B21: 3 | C21: =Principal!C24 -> FABRICACIONES [OTROS] | F21: 1 | G21: =Principal!E24*F21 -> 0
B22: 4 | C22: =Principal!C25 -> MONTAJE | F22: 1 | G22: =Principal!E25*F22 -> 0
B23: 5 | C23: =Principal!C26 -> 0 | F23: 1 | G23: =Principal!E26*F23 -> 0
B24: 6 | C24: =Principal!C27 -> 0 | F24: 1 | G24: =Principal!E27*F24 -> 0
B25: 7 | C25: =Principal!C28 -> 0 | F25: 1 | G25: =Principal!E28*F25 -> 0
B26: 8 | C26: =Principal!C29 -> TRANSPORTES | F26: 1 | G26: =Principal!E29*F26 -> 0
B27: 9 | F27: 0 | G27: =Principal!E30*F27 -> 0
B28: 10 | C28: =Principal!C31 -> 0 | F28: 0 | G28: =Principal!E31*F28 -> 0
E29: Total | G29: =SUM(G19:G28) -> 0

Sheet Cash Flow (Previsto)
B1: CASH FLOW
B3: Pagos del Cliente
B4: Concepto | C4: Descripción | D4: Presupuesto (BAC) | E4: Noviembre | F4: Diciembre | G4: Enero | H4: Febrero | I4: Marzo | J4: Abril | K4: Mayo | L4: Junio | M4: Julio | N4: Agosto | O4: Septiembre | P4: Octubre
B5: ='Forma de Pago'!C4 -> Anticipo | C5: ='Forma de Pago'!D4 -> 0 | D5: ='Forma de Pago'!G4 -> 0
B6: ='Forma de Pago'!C5 -> Entrega | C6: ='Forma de Pago'!D5 -> 0 | D6: ='Forma de Pago'!G5 -> 0
B7: ='Forma de Pago'!C6 -> Finalización | C7: ='Forma de Pago'!D6 -> 0 | D7: ='Forma de Pago'!G6 -> 0
B8: ='Forma de Pago'!C7 -> 0 | C8: ='Forma de Pago'!D7 -> 0 | D8: ='Forma de Pago'!G7 -> 0
B9: ='Forma de Pago'!C8 -> 0 | C9: ='Forma de Pago'!D8 -> 0 | D9: ='Forma de Pago'!G8 -> 0
B10: ='Forma de Pago'!C9 -> 0 | C10: ='Forma de Pago'!D9 -> 0 | D10: =SUM(E10:P10) -> 0
B11: ='Forma de Pago'!C10 -> 0 | C11: ='Forma de Pago'!D10 -> 0 | D11: =SUM(E11:P11) -> 0
B12: ='Forma de Pago'!C11 -> 0 | C12: ='Forma de Pago'!D11 -> 0 | D12: =SUM(E12:P12) -> 0
B13: ='Forma de Pago'!C12 -> 0 | C13: ='Forma de Pago'!D12 -> 0 | D13: =SUM(E13:P13) -> 0
B14: ='Forma de Pago'!C13 -> 0 | C14: ='Forma de Pago'!D13 -> 0 | D14: =SUM(E14:P14) -> 0
B15: Total | D15: =SUM(D5:D14) -> 0
B16: Pagos a Proveedores
B17: Concepto | C17: Descripción | D17: Presupuesto (BAC) | E17: =E4 -> Noviembre | F17: =F4 -> Diciembre | G17: =G4 -> Enero | H17: =H4 -> Febrero | I17: =I4 -> Marzo | J17: =J4 -> Abril | K17: =K4 -> Mayo | L17: =L4 -> Junio | ... P17: =P4 -> Octubre
B18: ='Forma de Pago'!C19 -> FABRICACIONES TANQUES | C18: ='Forma de Pago'!D19 -> 0 | D18: =-('Forma de Pago'!G19) -> 0
B19: ='Forma de Pago'!C20 -> FABRICACIONES TECHOS | C19: ='Forma de Pago'!D20 -> 0 | D19: =-('Forma de Pago'!G20) -> 0
B20: ='Forma de Pago'!C21 -> FABRICACIONES [OTROS] | C20: ='Forma de Pago'!D21 -> 0 | D20: =-('Forma de Pago'!G21) -> 0
B21: ='Forma de Pago'!C22 -> MONTAJE | C21: ='Forma de Pago'!D22 -> 0 | D21: =-('Forma de Pago'!G22) -> 0
B22: ='Forma de Pago'!C23 -> 0 | C22: ='Forma de Pago'!D23 -> 0 | D22: =-('Forma de Pago'!G23) -> 0
B23: ='Forma de Pago'!C24 -> 0 | C23: ='Forma de Pago'!D24 -> 0 | D23: =-('Forma de Pago'!G24) -> 0
B24: ='Forma de Pago'!C25 -> 0 | C24: ='Forma de Pago'!D25 -> 0 | D24: =-('Forma de Pago'!G25) -> 0
B25: ='Forma de Pago'!C26 -> TRANSPORTES | C25: ='Forma de Pago'!D26 -> 0 | D25: =-('Forma de Pago'!G26) -> 0
B26: ='Forma de Pago'!C27 -> 0 | C26: ='Forma de Pago'!D27 -> 0 | D26: =-('Forma de Pago'!G27) -> 0
B27: ='Forma de Pago'!C28 -> 0 | C27: ='Forma de Pago'!D28 -> 0 | D27: =-('Forma de Pago'!G28) -> 0
B29: Total | D29: =SUM(D18:D28) -> 0
E30: =SUM(E5:E27) -> 0 | F30: =SUM(F5:F27) -> 0 | G30: =SUM(G5:G27) -> 0 | H30: =SUM(H5:H27) -> 0 | I30: =SUM(I5:I27) -> 0 | J30: =SUM(J5:J27) -> 0 | K30: =SUM(K5:K27) -> 0 | L30: =SUM(L5:L27) -> 0 | ... P30: =SUM(P5:P27) -> 0
B32: FLUJO DE CAJA | E32: =SUM($E$30:E30) -> 0 | F32: =SUM($E$30:F30) -> 0 | G32: =SUM($E$30:G30) -> 0 | H32: =SUM($E$30:H30) -> 0 | I32: =SUM($E$30:I30) -> 0 | J32: =SUM($E$30:J30) -> 0 | K32: =SUM($E$30:K30) -> 0 | L32: =SUM($E$30:L30) -> 0 | ... P32: =SUM($E$30:P30) -> 0
B36: Revisiones | D36: Descripción
B37: 0
B38: 1
B39: 2
B40: 3
B41: 4
B42: 5

Sheet Cash Flow (Actual)
B1: CASH FLOW
B3: Pagos del Cliente
B4: Concepto | C4: Descripción | D4: Presupuesto (BAC) | E4: ='Cash Flow (Previsto)'!E4 -> Noviembre | F4: ='Cash Flow (Previsto)'!F4 -> Diciembre | G4: ='Cash Flow (Previsto)'!G4 -> Enero | H4: ='Cash Flow (Previsto)'!H4 -> Febrero | I4: ='Cash Flow (Previsto)'!I4 -> Marzo | J4: ='Cash Flow (Previsto)'!J4 -> Abril | K4: ='Cash Flow (Previsto)'!K4 -> Mayo | L4: ='Cash Flow (Previsto)'!L4 -> Junio | ... P4: ='Cash Flow (Previsto)'!P4 -> Octubre
B5: ='Forma de Pago'!C4 -> Anticipo | C5: ='Forma de Pago'!D4 -> 0 | D5: ='Forma de Pago'!G4 -> 0
B6: ='Forma de Pago'!C5 -> Entrega | C6: ='Forma de Pago'!D5 -> 0 | D6: ='Forma de Pago'!G5 -> 0
B7: ='Forma de Pago'!C6 -> Finalización | C7: ='Forma de Pago'!D6 -> 0 | D7: ='Forma de Pago'!G6 -> 0
B8: ='Forma de Pago'!C7 -> 0 | C8: ='Forma de Pago'!D7 -> 0 | D8: ='Forma de Pago'!G7 -> 0
B9: ='Forma de Pago'!C8 -> 0 | C9: ='Forma de Pago'!D8 -> 0 | D9: ='Forma de Pago'!G8 -> 0
B10: ='Forma de Pago'!C9 -> 0 | C10: ='Forma de Pago'!D9 -> 0 | D10: =SUM(E10:P10) -> 0
B11: ='Forma de Pago'!C10 -> 0 | C11: ='Forma de Pago'!D10 -> 0 | D11: =SUM(E11:P11) -> 0
B12: ='Forma de Pago'!C11 -> 0 | C12: ='Forma de Pago'!D11 -> 0 | D12: =SUM(E12:P12) -> 0
B13: ='Forma de Pago'!C12 -> 0 | C13: ='Forma de Pago'!D12 -> 0 | D13: =SUM(E13:P13) -> 0
B14: ='Forma de Pago'!C13 -> 0 | C14: ='Forma de Pago'!D13 -> 0 | D14: =SUM(E14:P14) -> 0
B15: Total | D15: =SUM(D5:D14) -> 0
B16: Pagos a Proveedores
B17: Concepto | C17: Descripción | D17: Presupuesto (BAC) | E17: =E4 -> Noviembre | F17: =F4 -> Diciembre | G17: =G4 -> Enero | H17: =H4 -> Febrero | I17: =I4 -> Marzo | J17: =J4 -> Abril | K17: =K4 -> Mayo | L17: =L4 -> Junio | ... P17: =P4 -> Octubre
B18: ='Forma de Pago'!C19 -> FABRICACIONES TANQUES | C18: ='Forma de Pago'!D19 -> 0 | D18: =-'Forma de Pago'!G19 -> 0
B19: ='Forma de Pago'!C20 -> FABRICACIONES TECHOS | C19: ='Forma de Pago'!D20 -> 0 | D19: =-'Forma de Pago'!G20 -> 0
B20: ='Forma de Pago'!C21 -> FABRICACIONES [OTROS] | C20: ='Forma de Pago'!D21 -> 0 | D20: =-'Forma de Pago'!G21 -> 0
B21: ='Forma de Pago'!C22 -> MONTAJE | C21: ='Forma de Pago'!D22 -> 0 | D21: ='Forma de Pago'!G22 -> 0
B22: ='Forma de Pago'!C23 -> 0 | C22: ='Forma de Pago'!D23 -> 0 | D22: ='Forma de Pago'!G23 -> 0
B23: ='Forma de Pago'!C24 -> 0 | C23: ='Forma de Pago'!D24 -> 0 | D23: ='Forma de Pago'!G24 -> 0
B24: ='Forma de Pago'!C25 -> 0 | C24: ='Forma de Pago'!D25 -> 0 | D24: ='Forma de Pago'!G25 -> 0
B25: ='Forma de Pago'!C26 -> TRANSPORTES | C25: ='Forma de Pago'!D26 -> 0 | D25: ='Forma de Pago'!G26 -> 0
B26: ='Forma de Pago'!C27 -> 0 | C26: ='Forma de Pago'!D27 -> 0 | D26: ='Forma de Pago'!G27 -> 0
B27: ='Forma de Pago'!C28 -> 0 | C27: ='Forma de Pago'!D28 -> 0 | D27: ='Forma de Pago'!G28 -> 0
B29: Total | D29: =SUM(D18:D28) -> 0
E30: =SUM(E5:E27) -> 0 | F30: =SUM(F5:F27) -> 0 | G30: =SUM(G5:G27) -> 0 | H30: =SUM(H5:H27) -> 0 | I30: =SUM(I5:I27) -> 0 | J30: =SUM(J5:J27) -> 0 | K30: =SUM(K5:K27) -> 0 | L30: =SUM(L5:L27) -> 0 | ... P30: =SUM(P5:P27) -> 0
B32: FLUJO DE CAJA | E32: =SUM($E$30:E30) -> 0 | F32: =SUM($E$30:F30) -> 0 | G32: =SUM($E$30:G30) -> 0 | H32: =SUM($E$30:H30) -> 0 | I32: =SUM($E$30:I30) -> 0 | J32: =SUM($E$30:J30) -> 0 | K32: =SUM($E$30:K30) -> 0 | L32: =SUM($E$30:L30) -> 0 | ... P32: =SUM($E$30:P30) -> 0
B36: Revisiones | D36: Descripción
B37: 0
B38: 1
B39: 2
B40: 3
B41: 4
B42: 5
